[{"deutsch":"Jahrhundert, Menschalter, Zeit(alter)","fremdsprache":"saeculum, saeculi"},{"deutsch":"ganz","fremdsprache":"totus, a, um"},{"deutsch":"in ganz Italien (wo?)","fremdsprache":"tota Italia"},{"deutsch":"im ganzen Reich (wo?)","fremdsprache":"toto imperio"},{"deutsch":"Familienverband, Stamm, Volk","fremdsprache":"gens, gentis f."},{"deutsch":"Sitte, Brauch (Pl. Charakter)","fremdsprache":"mos, moris m."},{"deutsch":"aufschreiben, verfassen","fremdsprache":"conscribere, conscribo, conscripsi, conscriptum"},{"deutsch":"Soldaten ausheben","fremdsprache":"milites conscribere"},{"deutsch":"an vielen Orten (wo?)","fremdsprache":"multis locis"},{"deutsch":"Lager","fremdsprache":"castra, castrorum Pl.n."},{"deutsch":"aufstellen, unterbringen","fremdsprache":"collocare, colloco, collocavi, collocatum"},{"deutsch":"das Lager aufschlagen","fremdsprache":"castra collocare"},{"deutsch":"Kohorte (bis zu 600 Mann)","fremdsprache":"cohors, cohortis f."},{"deutsch":"von/ aus Rom (weg) (woher?)","fremdsprache":"Roma"},{"deutsch":"(los)lassen, schicken; werfen","fremdsprache":"mittere, mitto, misi, missum"},{"deutsch":"Provinz","fremdsprache":"provincia, provinciae"},{"deutsch":"in Rom (wo?)","fremdsprache":"Romae"},{"deutsch":"Bau, Befestigung","fremdsprache":"munitio, munitionis f."},{"deutsch":"nennen, bezeichnen (als)","fremdsprache":"dicere, vocare, appellare m.dopp.Akk."},{"deutsch":"hindern, verhindern","fremdsprache":"impedire, impedio, impedivi, impeditum"},{"deutsch":"Heereszug, Zug","fremdsprache":"agmen, agminis n."},{"deutsch":"nach Weissenburg (wohin?)","fremdsprache":"Biricianam"},{"deutsch":"Reise, Marsch, Weg","fremdsprache":"iter, itineris n."},{"deutsch":"eine Reise machen","fremdsprache":"iter facere"},{"deutsch":"Monat","fremdsprache":"mensis, mensis m. (Gen. -ium)"},{"deutsch":"auf sich nehmen, sich (einer Sache) annehmen, unternehmen","fremdsprache":"suscipere, suscipio, suscepi, susceptum"},{"deutsch":"halten für","fremdsprache":"ducere, putare m.dopp.Akk."},{"deutsch":"Belohnung, Lohn","fremdsprache":"praemium, praemii"},{"deutsch":"Gemeinde, Staat, Bürgerrecht","fremdsprache":"civitas, civitatis f."},{"deutsch":"zum Tode verurteilen","fremdsprache":"capitis damnare"},{"deutsch":"Befehlshaber, Feldherr, Kaiser","fremdsprache":"imperator, imperatoris m."},{"deutsch":"machen zu","fremdsprache":"facere m.dopp.Akk."},{"deutsch":"öffentlich, staatlich","fremdsprache":"publicus, a, um"},{"deutsch":"Staat","fremdsprache":"res publica"},{"deutsch":"sich dem Staatsdienst widmen","fremdsprache":"ad rem publicam accedere"},{"deutsch":"Ämterlaufbahn","fremdsprache":"cursus honorum"},{"deutsch":"kaufen","fremdsprache":"emere, emo, emi, emptum"}]