[{"deutsch":"(sich) aufhalten","fremdsprache":"morari,moror,mortatus sum"},{"deutsch":"Fähigkeit;Möglichkeit","fremdsprache":"facultas,facultatis f"},{"deutsch":"Dienerin/Sklavin","fremdsprache":"ancilla"},{"deutsch":"hinzufügen,anschließen","fremdsprache":"adiungere,adiungo,adiunxi,adiunctum"},{"deutsch":"meistens","fremdsprache":"plerumque Adv."},{"deutsch":"irgendjemand(in verneinten Sätzen)","fremdsprache":"quisquam,quaequam,quidquam (quicquam)"},{"deutsch":"und niemand","fremdsprache":"nec quisquam"},{"deutsch":"vermuten, ahnen","fremdsprache":"suspicari,suspicor"},{"deutsch":"geheim,verborgen","fremdsprache":"occultus,a,um"},{"deutsch":"nächtlich","fremdsprache":"nocturnus,a,um"}]